pynamodb_mypy/__init__.py
pynamodb_mypy/_private_api.py
pynamodb_mypy/plugin.py
pynamodb_mypy-0.1.2.dist-info/LICENSE
pynamodb_mypy-0.1.2.dist-info/METADATA
pynamodb_mypy-0.1.2.dist-info/WHEEL
pynamodb_mypy-0.1.2.dist-info/top_level.txt
pynamodb_mypy-0.1.2.dist-info/RECORD
