Metadata-Version: 2.1
Name: pynamodb-mypy
Version: 0.1.2
Summary: mypy plugin for PynamoDB
Home-page: https://www.github.com/pynamodb/pynamodb-mypy
Maintainer: Ilya Priven
Maintainer-email: ilya.konstantinov@gmail.com
Classifier: Programming Language :: Python :: 3
Classifier: Programming Language :: Python :: 3 :: Only
Classifier: Programming Language :: Python :: 3.8
Requires-Python: >=3.8
License-File: LICENSE
Requires-Dist: mypy (>=0.940)
